databao/__init__.py
databao/api.py
databao/py.typed
databao/caches/__init__.py
databao/caches/disk_cache.py
databao/caches/in_mem_cache.py
databao/configs/__init__.py
databao/configs/llm.py
databao/core/__init__.py
databao/core/agent.py
databao/core/cache.py
databao/core/data_source.py
databao/core/executor.py
databao/core/opa.py
databao/core/thread.py
databao/core/visualizer.py
databao/duckdb/__init__.py
databao/duckdb/react_tools.py
databao/duckdb/utils.py
databao/executors/__init__.py
databao/executors/base.py
databao/executors/frontend/__init__.py
databao/executors/frontend/messages.py
databao/executors/frontend/text_frontend.py
databao/executors/lighthouse/__init__.py
databao/executors/lighthouse/executor.py
databao/executors/lighthouse/graph.py
databao/executors/lighthouse/history_cleaning.py
databao/executors/lighthouse/system_prompt.jinja
databao/executors/lighthouse/utils.py
databao/executors/react_duckdb/__init__.py
databao/executors/react_duckdb/executor.py
databao/visualizers/__init__.py
databao/visualizers/dumb.py
databao/visualizers/vega_chat.py
databao/visualizers/vega_vis_tool.py
databao-0.1.3.dist-info/METADATA
databao-0.1.3.dist-info/WHEEL
databao-0.1.3.dist-info/licenses/LICENSE.md
databao-0.1.3.dist-info/RECORD
