Metadata-Version: 2.4
Name: databao
Version: 0.1.3
Summary: databao: NL queries for data
Project-URL: Homepage, https://databao.app/
Project-URL: Source, https://github.com/JetBrains/databao
License-Expression: Apache-2.0 AND LicenseRef-Additional-Terms
License-File: LICENSE.md
Classifier: Operating System :: OS Independent
Classifier: Programming Language :: Python :: 3
Requires-Python: <3.15,>=3.10
Requires-Dist: diskcache>=5.6.3
Requires-Dist: duckdb>=1.3.0
Requires-Dist: edaplot-vl~=0.1.4
Requires-Dist: jinja2>=3.1.6
Requires-Dist: langchain-anthropic>=1.3.0
Requires-Dist: langchain-ollama>=1.0.0
Requires-Dist: langchain-openai>=1.1.3
Requires-Dist: langchain>=1.1.3
Requires-Dist: langgraph>=0.6.8
Requires-Dist: matplotlib>=3.10.0
Requires-Dist: pandas>=2.2.2
Requires-Dist: psycopg2-binary>=2.9.10
Requires-Dist: pydantic<3,>=2.8.0
Requires-Dist: sqlalchemy>=2.0.45
Requires-Dist: tabulate>=0.9.0
Provides-Extra: examples
Requires-Dist: notebook>=7.4.7; extra == 'examples'
Requires-Dist: python-dotenv>=1.1.1; extra == 'examples'
